nat/meta/pypi.md
nat/plugins/phoenix/__init__.py
nat/plugins/phoenix/phoenix_exporter.py
nat/plugins/phoenix/register.py
nat/plugins/phoenix/mixin/__init__.py
nat/plugins/phoenix/mixin/phoenix_mixin.py
nvidia_nat_phoenix-1.3.1.dist-info/licenses/LICENSE-3rd-party.txt
nvidia_nat_phoenix-1.3.1.dist-info/licenses/LICENSE.md
nvidia_nat_phoenix-1.3.1.dist-info/METADATA
nvidia_nat_phoenix-1.3.1.dist-info/WHEEL
nvidia_nat_phoenix-1.3.1.dist-info/entry_points.txt
nvidia_nat_phoenix-1.3.1.dist-info/top_level.txt
nvidia_nat_phoenix-1.3.1.dist-info/RECORD
