Metadata-Version: 2.4
Name: nvidia-nat-phoenix
Version: 1.3.1
Summary: Subpackage for Arize Phoenix integration in NeMo Agent toolkit
Author: NVIDIA Corporation
Maintainer: NVIDIA Corporation
License: Apache-2.0
Project-URL: documentation, https://docs.nvidia.com/nemo/agent-toolkit/latest/
Project-URL: source, https://github.com/NVIDIA/NeMo-Agent-Toolkit
Keywords: ai,observability,phoenix,arize
Classifier: Programming Language :: Python
Classifier: Programming Language :: Python :: 3.11
Classifier: Programming Language :: Python :: 3.12
Classifier: Programming Language :: Python :: 3.13
Requires-Python: <3.14,>=3.11
License-File: LICENSE-3rd-party.txt
License-File: LICENSE.md
Requires-Dist: nvidia-nat[opentelemetry]==v1.3.1
Requires-Dist: arize-phoenix-otel~=0.13.1
Requires-Dist: openinference-instrumentation
Dynamic: license-file
